{
  "subscriptions": [
    {
      "name": "지재처 관련뉴스",
      "groups": [
        [
          "지식재산처",
          "지재처",
          "특허청",
          "WIPO",
          "상표 분쟁",
          "특허 소송"
        ]
      ]
    },
    {
      "name": "AI·지식재산",
      "groups": [
        [
          "AI",
          "인공지능"
        ],
        [
          "지식재산",
          "특허",
          "상표",
          "디자인"
        ]
      ]
    },
    {
      "name": "AI 업계",
      "groups": [
        [
          "오픈AI",
          "챗GPT",
          "앤스로픽",
          "클로드",
          "제미나이",
          "엔비디아",
          "생성형 AI"
        ]
      ]
    }
  ]
}